MANIFEST.in
setup.py
django_gubbins.egg-info/PKG-INFO
django_gubbins.egg-info/SOURCES.txt
django_gubbins.egg-info/dependency_links.txt
django_gubbins.egg-info/requires.txt
django_gubbins.egg-info/top_level.txt
gubbins/__init__.py
gubbins/app.py
gubbins/models.py
gubbins/utils.py
gubbins/db/__init__.py
gubbins/db/field.py
gubbins/db/manager.py
gubbins/db/queryset.py
gubbins/db/utils.py
gubbins/files/__init__.py
gubbins/files/uploadhandler.py