Metadata-Version: 1.0
Name: django-gubbins
Version: 1.1
Summary: A collection of useful snippets for enhancing or replacing functionality within Django
Home-page: https://github.com/carlio/django-gubbins
Author: Carl Crowder
Author-email: django-gubbins@jqx.be
License: BSD
Keywords: django
Platform: UNKNOWN
